{
  "batch_id": "6176d729ad4010af",
  "timestamp": "2025-09-06T11:50:59.431Z",
  "session_id": "session_1757142070776_0dhi4qwvr",
  "events": [
    {
      "id": "5e7e837edc9d467e",
      "type": "state_change",
      "timestamp": "2025-09-06T11:50:59.332Z",
      "session_id": "session_1757142070776_0dhi4qwvr",
      "file_path": "/Users/kavi/Sharedcodingprojects/Muralla-4.0/.shared-state/sessions/session_1757142070776_0dhi4qwvr.json",
      "change_type": "modification"
    },
    {
      "id": "84598e8ec877c093",
      "type": "state_change",
      "timestamp": "2025-09-06T11:50:59.431Z",
      "session_id": "session_1757142070776_0dhi4qwvr",
      "file_path": "/Users/kavi/Sharedcodingprojects/Muralla-4.0/.shared-state/sessions/session_1757142070776_0dhi4qwvr.json",
      "change_type": "modification"
    }
  ]
}