{
  "batch_id": "12f1910a8f17d81b",
  "timestamp": "2025-09-06T09:02:53.307Z",
  "session_id": "session_1757142070776_0dhi4qwvr",
  "events": [
    {
      "id": "a3d537fc2e04f9fb",
      "type": "state_change",
      "timestamp": "2025-09-06T09:02:53.206Z",
      "session_id": "session_1757142070776_0dhi4qwvr",
      "file_path": "/Users/kavi/Sharedcodingprojects/Muralla-4.0/.shared-state/sessions/session_1757142070776_0dhi4qwvr.json",
      "change_type": "modification"
    },
    {
      "id": "6f489d1476a00bc2",
      "type": "state_change",
      "timestamp": "2025-09-06T09:02:53.306Z",
      "session_id": "session_1757142070776_0dhi4qwvr",
      "file_path": "/Users/kavi/Sharedcodingprojects/Muralla-4.0/.shared-state/sessions/session_1757142070776_0dhi4qwvr.json",
      "change_type": "modification"
    }
  ]
}