{
  "batch_id": "35ceb744d7f15c17",
  "timestamp": "2025-09-06T13:56:37.636Z",
  "session_id": "session_1757142070776_0dhi4qwvr",
  "events": [
    {
      "id": "a79f6d7c3ca0a56a",
      "type": "state_change",
      "timestamp": "2025-09-06T13:56:37.542Z",
      "session_id": "session_1757142070776_0dhi4qwvr",
      "file_path": "/Users/kavi/Sharedcodingprojects/Muralla-4.0/.shared-state/sessions/session_1757142070776_0dhi4qwvr.json",
      "change_type": "modification"
    },
    {
      "id": "497e895392cb267b",
      "type": "state_change",
      "timestamp": "2025-09-06T13:56:37.635Z",
      "session_id": "session_1757142070776_0dhi4qwvr",
      "file_path": "/Users/kavi/Sharedcodingprojects/Muralla-4.0/.shared-state/sessions/session_1757142070776_0dhi4qwvr.json",
      "change_type": "modification"
    }
  ]
}