{
  "batch_id": "f845df47d2e778fe",
  "timestamp": "2025-09-06T12:09:19.307Z",
  "session_id": "session_1757142070776_0dhi4qwvr",
  "events": [
    {
      "id": "e86e59a9c0fd2003",
      "type": "state_change",
      "timestamp": "2025-09-06T12:09:19.206Z",
      "session_id": "session_1757142070776_0dhi4qwvr",
      "file_path": "/Users/kavi/Sharedcodingprojects/Muralla-4.0/.shared-state/sessions/session_1757142070776_0dhi4qwvr.json",
      "change_type": "modification"
    },
    {
      "id": "6513ca7bd980f573",
      "type": "state_change",
      "timestamp": "2025-09-06T12:09:19.306Z",
      "session_id": "session_1757142070776_0dhi4qwvr",
      "file_path": "/Users/kavi/Sharedcodingprojects/Muralla-4.0/.shared-state/sessions/session_1757142070776_0dhi4qwvr.json",
      "change_type": "modification"
    }
  ]
}