{
  "batch_id": "7ecb367604492f23",
  "timestamp": "2025-09-06T11:54:01.240Z",
  "session_id": "session_1757142070776_0dhi4qwvr",
  "events": [
    {
      "id": "02f74b233d2b199f",
      "type": "state_change",
      "timestamp": "2025-09-06T11:54:01.138Z",
      "session_id": "session_1757142070776_0dhi4qwvr",
      "file_path": "/Users/kavi/Sharedcodingprojects/Muralla-4.0/.shared-state/sessions/session_1757142070776_0dhi4qwvr.json",
      "change_type": "modification"
    },
    {
      "id": "20fa507fcc13b1f6",
      "type": "state_change",
      "timestamp": "2025-09-06T11:54:01.240Z",
      "session_id": "session_1757142070776_0dhi4qwvr",
      "file_path": "/Users/kavi/Sharedcodingprojects/Muralla-4.0/.shared-state/sessions/session_1757142070776_0dhi4qwvr.json",
      "change_type": "modification"
    }
  ]
}