{
  "batch_id": "7dde78cb5e363ffb",
  "timestamp": "2025-09-06T14:46:10.743Z",
  "session_id": "session_1757142070776_0dhi4qwvr",
  "events": [
    {
      "id": "070a637eecc2a411",
      "type": "state_change",
      "timestamp": "2025-09-06T14:46:10.642Z",
      "session_id": "session_1757142070776_0dhi4qwvr",
      "file_path": "/Users/kavi/Sharedcodingprojects/Muralla-4.0/.shared-state/sessions/session_1757142070776_0dhi4qwvr.json",
      "change_type": "modification"
    },
    {
      "id": "0cae1d13214e5a47",
      "type": "state_change",
      "timestamp": "2025-09-06T14:46:10.742Z",
      "session_id": "session_1757142070776_0dhi4qwvr",
      "file_path": "/Users/kavi/Sharedcodingprojects/Muralla-4.0/.shared-state/sessions/session_1757142070776_0dhi4qwvr.json",
      "change_type": "modification"
    }
  ]
}