{
  "batch_id": "eda1c8891345e97a",
  "timestamp": "2025-09-06T15:29:44.282Z",
  "session_id": "session_1757142070776_0dhi4qwvr",
  "events": [
    {
      "id": "d30ad77322347393",
      "type": "state_change",
      "timestamp": "2025-09-06T15:29:44.182Z",
      "session_id": "session_1757142070776_0dhi4qwvr",
      "file_path": "/Users/kavi/Sharedcodingprojects/Muralla-4.0/.shared-state/sessions/session_1757142070776_0dhi4qwvr.json",
      "change_type": "modification"
    },
    {
      "id": "c6731c5f7a30692c",
      "type": "state_change",
      "timestamp": "2025-09-06T15:29:44.282Z",
      "session_id": "session_1757142070776_0dhi4qwvr",
      "file_path": "/Users/kavi/Sharedcodingprojects/Muralla-4.0/.shared-state/sessions/session_1757142070776_0dhi4qwvr.json",
      "change_type": "modification"
    }
  ]
}