{
  "batch_id": "fad5e98e4422eb39",
  "timestamp": "2025-09-06T12:14:00.530Z",
  "session_id": "session_1757142070776_0dhi4qwvr",
  "events": [
    {
      "id": "94196e62a5ba40f5",
      "type": "state_change",
      "timestamp": "2025-09-06T12:14:00.431Z",
      "session_id": "session_1757142070776_0dhi4qwvr",
      "file_path": "/Users/kavi/Sharedcodingprojects/Muralla-4.0/.shared-state/sessions/session_1757142070776_0dhi4qwvr.json",
      "change_type": "modification"
    },
    {
      "id": "7f69bbd04d57d719",
      "type": "state_change",
      "timestamp": "2025-09-06T12:14:00.530Z",
      "session_id": "session_1757142070776_0dhi4qwvr",
      "file_path": "/Users/kavi/Sharedcodingprojects/Muralla-4.0/.shared-state/sessions/session_1757142070776_0dhi4qwvr.json",
      "change_type": "modification"
    }
  ]
}