{
  "batch_id": "b9682986338510ea",
  "timestamp": "2025-09-06T07:09:56.579Z",
  "session_id": "session_1757142070776_0dhi4qwvr",
  "events": [
    {
      "id": "866d8c2c9c686631",
      "type": "state_change",
      "timestamp": "2025-09-06T07:09:56.478Z",
      "session_id": "session_1757142070776_0dhi4qwvr",
      "file_path": "/Users/kavi/Sharedcodingprojects/Muralla-4.0/.shared-state/sessions/session_1757142070776_0dhi4qwvr.json",
      "change_type": "modification"
    },
    {
      "id": "00fbbf1329646998",
      "type": "state_change",
      "timestamp": "2025-09-06T07:09:56.579Z",
      "session_id": "session_1757142070776_0dhi4qwvr",
      "file_path": "/Users/kavi/Sharedcodingprojects/Muralla-4.0/.shared-state/sessions/session_1757142070776_0dhi4qwvr.json",
      "change_type": "modification"
    }
  ]
}