{
  "batch_id": "86518b80a26d5654",
  "timestamp": "2025-09-06T16:26:40.659Z",
  "session_id": "session_1757142070776_0dhi4qwvr",
  "events": [
    {
      "id": "4b1a6f43406a4f85",
      "type": "state_change",
      "timestamp": "2025-09-06T16:26:40.558Z",
      "session_id": "session_1757142070776_0dhi4qwvr",
      "file_path": "/Users/kavi/Sharedcodingprojects/Muralla-4.0/.shared-state/sessions/session_1757142070776_0dhi4qwvr.json",
      "change_type": "modification"
    },
    {
      "id": "f211811eca2a016e",
      "type": "state_change",
      "timestamp": "2025-09-06T16:26:40.659Z",
      "session_id": "session_1757142070776_0dhi4qwvr",
      "file_path": "/Users/kavi/Sharedcodingprojects/Muralla-4.0/.shared-state/sessions/session_1757142070776_0dhi4qwvr.json",
      "change_type": "modification"
    }
  ]
}