{
  "batch_id": "f94fb562dfce7626",
  "timestamp": "2025-09-06T15:33:58.137Z",
  "session_id": "session_1757142070776_0dhi4qwvr",
  "events": [
    {
      "id": "780eb01c667dccc3",
      "type": "state_change",
      "timestamp": "2025-09-06T15:33:58.037Z",
      "session_id": "session_1757142070776_0dhi4qwvr",
      "file_path": "/Users/kavi/Sharedcodingprojects/Muralla-4.0/.shared-state/sessions/session_1757142070776_0dhi4qwvr.json",
      "change_type": "modification"
    },
    {
      "id": "ddc3986bfc6c0541",
      "type": "state_change",
      "timestamp": "2025-09-06T15:33:58.037Z",
      "session_id": "session_1757142070776_0dhi4qwvr",
      "file_path": "/Users/kavi/Sharedcodingprojects/Muralla-4.0/.shared-state/sessions/vscode-MacBook-Pro-de-Kavi.local-1757098522161.json",
      "change_type": "modification"
    },
    {
      "id": "6ee08beabce58c81",
      "type": "state_change",
      "timestamp": "2025-09-06T15:33:58.137Z",
      "session_id": "session_1757142070776_0dhi4qwvr",
      "file_path": "/Users/kavi/Sharedcodingprojects/Muralla-4.0/.shared-state/sessions/session_1757142070776_0dhi4qwvr.json",
      "change_type": "modification"
    }
  ]
}