{
  "batch_id": "1232cb79dffdc4fc",
  "timestamp": "2025-09-06T16:44:41.589Z",
  "session_id": "session_1757142070776_0dhi4qwvr",
  "events": [
    {
      "id": "6aa120cc324fdec5",
      "type": "state_change",
      "timestamp": "2025-09-06T16:44:41.487Z",
      "session_id": "session_1757142070776_0dhi4qwvr",
      "file_path": "/Users/kavi/Sharedcodingprojects/Muralla-4.0/.shared-state/sessions/session_1757142070776_0dhi4qwvr.json",
      "change_type": "modification"
    },
    {
      "id": "689b9451c841ac3a",
      "type": "state_change",
      "timestamp": "2025-09-06T16:44:41.588Z",
      "session_id": "session_1757142070776_0dhi4qwvr",
      "file_path": "/Users/kavi/Sharedcodingprojects/Muralla-4.0/.shared-state/sessions/session_1757142070776_0dhi4qwvr.json",
      "change_type": "modification"
    }
  ]
}