{
  "batch_id": "0c25f201dbafd6c7",
  "timestamp": "2025-09-06T08:52:17.696Z",
  "session_id": "session_1757142070776_0dhi4qwvr",
  "events": [
    {
      "id": "8f3e169bc86986ae",
      "type": "state_change",
      "timestamp": "2025-09-06T08:52:17.595Z",
      "session_id": "session_1757142070776_0dhi4qwvr",
      "file_path": "/Users/kavi/Sharedcodingprojects/Muralla-4.0/.shared-state/sessions/session_1757142070776_0dhi4qwvr.json",
      "change_type": "modification"
    },
    {
      "id": "ae6f0bfa50e0cef1",
      "type": "state_change",
      "timestamp": "2025-09-06T08:52:17.695Z",
      "session_id": "session_1757142070776_0dhi4qwvr",
      "file_path": "/Users/kavi/Sharedcodingprojects/Muralla-4.0/.shared-state/sessions/session_1757142070776_0dhi4qwvr.json",
      "change_type": "modification"
    }
  ]
}