{
  "batch_id": "37b294cec006bf3b",
  "timestamp": "2025-09-06T08:37:02.195Z",
  "session_id": "session_1757142070776_0dhi4qwvr",
  "events": [
    {
      "id": "35e3459c0356727d",
      "type": "state_change",
      "timestamp": "2025-09-06T08:37:02.093Z",
      "session_id": "session_1757142070776_0dhi4qwvr",
      "file_path": "/Users/kavi/Sharedcodingprojects/Muralla-4.0/.shared-state/sessions/session_1757142070776_0dhi4qwvr.json",
      "change_type": "modification"
    },
    {
      "id": "7bda8d4059e4b820",
      "type": "state_change",
      "timestamp": "2025-09-06T08:37:02.194Z",
      "session_id": "session_1757142070776_0dhi4qwvr",
      "file_path": "/Users/kavi/Sharedcodingprojects/Muralla-4.0/.shared-state/sessions/session_1757142070776_0dhi4qwvr.json",
      "change_type": "modification"
    }
  ]
}