{
  "batch_id": "98dcdb1ee2d89078",
  "timestamp": "2025-09-06T10:18:02.525Z",
  "session_id": "session_1757142070776_0dhi4qwvr",
  "events": [
    {
      "id": "e6e4d1f0ebdee88f",
      "type": "state_change",
      "timestamp": "2025-09-06T10:18:02.424Z",
      "session_id": "session_1757142070776_0dhi4qwvr",
      "file_path": "/Users/kavi/Sharedcodingprojects/Muralla-4.0/.shared-state/sessions/session_1757142070776_0dhi4qwvr.json",
      "change_type": "modification"
    },
    {
      "id": "e3cfe282efbd045f",
      "type": "state_change",
      "timestamp": "2025-09-06T10:18:02.525Z",
      "session_id": "session_1757142070776_0dhi4qwvr",
      "file_path": "/Users/kavi/Sharedcodingprojects/Muralla-4.0/.shared-state/sessions/session_1757142070776_0dhi4qwvr.json",
      "change_type": "modification"
    }
  ]
}