{
  "batch_id": "f7bffd510bcb2492",
  "timestamp": "2025-09-06T09:51:27.646Z",
  "session_id": "session_1757142070776_0dhi4qwvr",
  "events": [
    {
      "id": "da02d34cf75e4d2c",
      "type": "state_change",
      "timestamp": "2025-09-06T09:51:27.544Z",
      "session_id": "session_1757142070776_0dhi4qwvr",
      "file_path": "/Users/kavi/Sharedcodingprojects/Muralla-4.0/.shared-state/sessions/session_1757142070776_0dhi4qwvr.json",
      "change_type": "modification"
    },
    {
      "id": "21649e5c83d97455",
      "type": "state_change",
      "timestamp": "2025-09-06T09:51:27.645Z",
      "session_id": "session_1757142070776_0dhi4qwvr",
      "file_path": "/Users/kavi/Sharedcodingprojects/Muralla-4.0/.shared-state/sessions/session_1757142070776_0dhi4qwvr.json",
      "change_type": "modification"
    }
  ]
}