{
  "batch_id": "823ac6d7369bd4e5",
  "timestamp": "2025-09-06T09:44:55.328Z",
  "session_id": "session_1757142070776_0dhi4qwvr",
  "events": [
    {
      "id": "39c47ebf7699bb23",
      "type": "state_change",
      "timestamp": "2025-09-06T09:44:55.239Z",
      "session_id": "session_1757142070776_0dhi4qwvr",
      "file_path": "/Users/kavi/Sharedcodingprojects/Muralla-4.0/.shared-state/sessions/vscode-MacBook-Pro-de-Kavi.local-1757098522161.json",
      "change_type": "modification"
    }
  ]
}