{
  "batch_id": "6486685119ac0914",
  "timestamp": "2025-09-06T12:02:52.402Z",
  "session_id": "session_1757142070776_0dhi4qwvr",
  "events": [
    {
      "id": "fe1ba3d955188d81",
      "type": "state_change",
      "timestamp": "2025-09-06T12:02:52.301Z",
      "session_id": "session_1757142070776_0dhi4qwvr",
      "file_path": "/Users/kavi/Sharedcodingprojects/Muralla-4.0/.shared-state/sessions/session_1757142070776_0dhi4qwvr.json",
      "change_type": "modification"
    },
    {
      "id": "1452e976d69e6dc7",
      "type": "state_change",
      "timestamp": "2025-09-06T12:02:52.401Z",
      "session_id": "session_1757142070776_0dhi4qwvr",
      "file_path": "/Users/kavi/Sharedcodingprojects/Muralla-4.0/.shared-state/sessions/session_1757142070776_0dhi4qwvr.json",
      "change_type": "modification"
    }
  ]
}