{
  "batch_id": "15e26247bb381203",
  "timestamp": "2025-09-06T15:33:20.160Z",
  "session_id": "session_1757142070776_0dhi4qwvr",
  "events": [
    {
      "id": "83decfa6a7ccd985",
      "type": "state_change",
      "timestamp": "2025-09-06T15:33:20.059Z",
      "session_id": "session_1757142070776_0dhi4qwvr",
      "file_path": "/Users/kavi/Sharedcodingprojects/Muralla-4.0/.shared-state/sessions/session_1757142070776_0dhi4qwvr.json",
      "change_type": "modification"
    },
    {
      "id": "df184c138d4e6ac5",
      "type": "state_change",
      "timestamp": "2025-09-06T15:33:20.159Z",
      "session_id": "session_1757142070776_0dhi4qwvr",
      "file_path": "/Users/kavi/Sharedcodingprojects/Muralla-4.0/.shared-state/sessions/session_1757142070776_0dhi4qwvr.json",
      "change_type": "modification"
    }
  ]
}