{
  "batch_id": "536525f1f258333c",
  "timestamp": "2025-09-06T09:12:08.160Z",
  "session_id": "session_1757142070776_0dhi4qwvr",
  "events": [
    {
      "id": "d2f0b45e0e876bda",
      "type": "state_change",
      "timestamp": "2025-09-06T09:12:08.059Z",
      "session_id": "session_1757142070776_0dhi4qwvr",
      "file_path": "/Users/kavi/Sharedcodingprojects/Muralla-4.0/.shared-state/sessions/session_1757142070776_0dhi4qwvr.json",
      "change_type": "modification"
    },
    {
      "id": "e8eaca5ccc33f3b8",
      "type": "state_change",
      "timestamp": "2025-09-06T09:12:08.159Z",
      "session_id": "session_1757142070776_0dhi4qwvr",
      "file_path": "/Users/kavi/Sharedcodingprojects/Muralla-4.0/.shared-state/sessions/session_1757142070776_0dhi4qwvr.json",
      "change_type": "modification"
    }
  ]
}