{
  "batch_id": "69397c0c6cf81b39",
  "timestamp": "2025-09-06T12:11:54.158Z",
  "session_id": "session_1757142070776_0dhi4qwvr",
  "events": [
    {
      "id": "829ef930bc6413f2",
      "type": "state_change",
      "timestamp": "2025-09-06T12:11:54.056Z",
      "session_id": "session_1757142070776_0dhi4qwvr",
      "file_path": "/Users/kavi/Sharedcodingprojects/Muralla-4.0/.shared-state/sessions/session_1757142070776_0dhi4qwvr.json",
      "change_type": "modification"
    },
    {
      "id": "9b32097763144292",
      "type": "state_change",
      "timestamp": "2025-09-06T12:11:54.157Z",
      "session_id": "session_1757142070776_0dhi4qwvr",
      "file_path": "/Users/kavi/Sharedcodingprojects/Muralla-4.0/.shared-state/sessions/session_1757142070776_0dhi4qwvr.json",
      "change_type": "modification"
    }
  ]
}