{
  "batch_id": "dd98e739cfdadaaa",
  "timestamp": "2025-09-06T10:28:02.414Z",
  "session_id": "session_1757142070776_0dhi4qwvr",
  "events": [
    {
      "id": "7bcaea6eb7fd2a43",
      "type": "state_change",
      "timestamp": "2025-09-06T10:28:02.314Z",
      "session_id": "session_1757142070776_0dhi4qwvr",
      "file_path": "/Users/kavi/Sharedcodingprojects/Muralla-4.0/.shared-state/sessions/session_1757142070776_0dhi4qwvr.json",
      "change_type": "modification"
    },
    {
      "id": "cec228adc962c3a0",
      "type": "state_change",
      "timestamp": "2025-09-06T10:28:02.414Z",
      "session_id": "session_1757142070776_0dhi4qwvr",
      "file_path": "/Users/kavi/Sharedcodingprojects/Muralla-4.0/.shared-state/sessions/session_1757142070776_0dhi4qwvr.json",
      "change_type": "modification"
    }
  ]
}