{
  "batch_id": "a79ab02f3f59d5bb",
  "timestamp": "2025-09-06T13:10:05.156Z",
  "session_id": "session_1757142070776_0dhi4qwvr",
  "events": [
    {
      "id": "7da90c5f9a686eaa",
      "type": "state_change",
      "timestamp": "2025-09-06T13:10:05.056Z",
      "session_id": "session_1757142070776_0dhi4qwvr",
      "file_path": "/Users/kavi/Sharedcodingprojects/Muralla-4.0/.shared-state/sessions/session_1757142070776_0dhi4qwvr.json",
      "change_type": "modification"
    },
    {
      "id": "3e538f8ad31712e6",
      "type": "state_change",
      "timestamp": "2025-09-06T13:10:05.156Z",
      "session_id": "session_1757142070776_0dhi4qwvr",
      "file_path": "/Users/kavi/Sharedcodingprojects/Muralla-4.0/.shared-state/sessions/session_1757142070776_0dhi4qwvr.json",
      "change_type": "modification"
    }
  ]
}