{
  "batch_id": "80db362d5e37e62a",
  "timestamp": "2025-09-07T06:40:53.258Z",
  "session_id": "session_1757142070776_0dhi4qwvr",
  "events": [
    {
      "id": "23c04b4dc78474f4",
      "type": "state_change",
      "timestamp": "2025-09-07T06:40:53.158Z",
      "session_id": "session_1757142070776_0dhi4qwvr",
      "file_path": "/Users/kavi/Sharedcodingprojects/Muralla-4.0/.shared-state/sessions/session_1757142070776_0dhi4qwvr.json",
      "change_type": "modification"
    },
    {
      "id": "4b62f34b3230ad9e",
      "type": "state_change",
      "timestamp": "2025-09-07T06:40:53.258Z",
      "session_id": "session_1757142070776_0dhi4qwvr",
      "file_path": "/Users/kavi/Sharedcodingprojects/Muralla-4.0/.shared-state/sessions/session_1757142070776_0dhi4qwvr.json",
      "change_type": "modification"
    }
  ]
}