{
  "batch_id": "d30101d202c1ddc8",
  "timestamp": "2025-09-06T13:25:44.494Z",
  "session_id": "session_1757142070776_0dhi4qwvr",
  "events": [
    {
      "id": "9071485e47cb649a",
      "type": "state_change",
      "timestamp": "2025-09-06T13:25:44.393Z",
      "session_id": "session_1757142070776_0dhi4qwvr",
      "file_path": "/Users/kavi/Sharedcodingprojects/Muralla-4.0/.shared-state/sessions/session_1757142070776_0dhi4qwvr.json",
      "change_type": "modification"
    },
    {
      "id": "ac952d672aaf48d6",
      "type": "state_change",
      "timestamp": "2025-09-06T13:25:44.494Z",
      "session_id": "session_1757142070776_0dhi4qwvr",
      "file_path": "/Users/kavi/Sharedcodingprojects/Muralla-4.0/.shared-state/sessions/session_1757142070776_0dhi4qwvr.json",
      "change_type": "modification"
    }
  ]
}