{
  "batch_id": "3111f79c39ce0efb",
  "timestamp": "2025-09-06T09:17:55.921Z",
  "session_id": "session_1757142070776_0dhi4qwvr",
  "events": [
    {
      "id": "da87e8b20ad3929e",
      "type": "state_change",
      "timestamp": "2025-09-06T09:17:55.819Z",
      "session_id": "session_1757142070776_0dhi4qwvr",
      "file_path": "/Users/kavi/Sharedcodingprojects/Muralla-4.0/.shared-state/sessions/session_1757142070776_0dhi4qwvr.json",
      "change_type": "modification"
    },
    {
      "id": "bbd02c536e94afdd",
      "type": "state_change",
      "timestamp": "2025-09-06T09:17:55.911Z",
      "session_id": "session_1757142070776_0dhi4qwvr",
      "file_path": "/Users/kavi/Sharedcodingprojects/Muralla-4.0/.shared-state/sessions/session_1757142070776_0dhi4qwvr.json",
      "change_type": "modification"
    }
  ]
}