{
  "batch_id": "8d06d6781c987c60",
  "timestamp": "2025-09-08T03:14:45.695Z",
  "session_id": "session_1757300624739_cz2adzlkj",
  "events": [
    {
      "id": "108070319cff555a",
      "type": "state_change",
      "timestamp": "2025-09-08T03:14:45.640Z",
      "session_id": "session_1757300624739_cz2adzlkj",
      "file_path": "/Users/kavi/Sharedcodingprojects/Muralla-4.0/.shared-state/.shared-state/sessions/session_1757300624739_cz2adzlkj.json",
      "change_type": "modification"
    }
  ]
}