{
  "batch_id": "5d71ce32d060c48a",
  "timestamp": "2025-09-08T03:07:18.275Z",
  "session_id": "session_1757300624739_cz2adzlkj",
  "events": [
    {
      "id": "72488d8128477c9a",
      "type": "state_change",
      "timestamp": "2025-09-08T03:07:18.199Z",
      "session_id": "session_1757300624739_cz2adzlkj",
      "file_path": "/Users/kavi/Sharedcodingprojects/Muralla-4.0/.shared-state/.shared-state/sessions/session_1757300624739_cz2adzlkj.json",
      "change_type": "modification"
    }
  ]
}