{
  "batch_id": "64d7dc06397daeab",
  "timestamp": "2025-09-08T03:11:32.501Z",
  "session_id": "session_1757300624739_cz2adzlkj",
  "events": [
    {
      "id": "c05a54e4bb332a72",
      "type": "state_change",
      "timestamp": "2025-09-08T03:11:32.424Z",
      "session_id": "session_1757300624739_cz2adzlkj",
      "file_path": "/Users/kavi/Sharedcodingprojects/Muralla-4.0/.shared-state/.shared-state/sessions/session_1757300624739_cz2adzlkj.json",
      "change_type": "modification"
    }
  ]
}