{
  "batch_id": "209d72e2a3b8423d",
  "timestamp": "2025-09-08T03:09:00.477Z",
  "session_id": "session_1757300624739_cz2adzlkj",
  "events": [
    {
      "id": "d32d11b4bccfae58",
      "type": "state_change",
      "timestamp": "2025-09-08T03:09:00.451Z",
      "session_id": "session_1757300624739_cz2adzlkj",
      "file_path": "/Users/kavi/Sharedcodingprojects/Muralla-4.0/.shared-state/.shared-state/sessions/session_1757300624739_cz2adzlkj.json",
      "change_type": "modification"
    }
  ]
}