{
  "batch_id": "41924c3f5b3da99d",
  "timestamp": "2025-09-08T03:07:52.594Z",
  "session_id": "session_1757300624739_cz2adzlkj",
  "events": [
    {
      "id": "0edbb5878ababa82",
      "type": "state_change",
      "timestamp": "2025-09-08T03:07:52.509Z",
      "session_id": "session_1757300624739_cz2adzlkj",
      "file_path": "/Users/kavi/Sharedcodingprojects/Muralla-4.0/.shared-state/.shared-state/sessions/session_1757300624739_cz2adzlkj.json",
      "change_type": "modification"
    }
  ]
}