{
  "batch_id": "eb45b7f6e778d28c",
  "timestamp": "2025-09-08T03:15:32.957Z",
  "session_id": "session_1757300624739_cz2adzlkj",
  "events": [
    {
      "id": "27774d5ae3978625",
      "type": "state_change",
      "timestamp": "2025-09-08T03:15:32.870Z",
      "session_id": "session_1757300624739_cz2adzlkj",
      "file_path": "/Users/kavi/Sharedcodingprojects/Muralla-4.0/.shared-state/.shared-state/sessions/session_1757300624739_cz2adzlkj.json",
      "change_type": "modification"
    }
  ]
}