{
  "batch_id": "d2642ee4f1f6f609",
  "timestamp": "2025-09-08T03:04:38.473Z",
  "session_id": "session_1757300624739_cz2adzlkj",
  "events": [
    {
      "id": "8ef1c4d23f2b0ae2",
      "type": "state_change",
      "timestamp": "2025-09-08T03:04:38.443Z",
      "session_id": "session_1757300624739_cz2adzlkj",
      "file_path": "/Users/kavi/Sharedcodingprojects/Muralla-4.0/.shared-state/.shared-state/sessions/session_1757300624739_cz2adzlkj.json",
      "change_type": "modification"
    }
  ]
}