{
  "batch_id": "f3746d0fdca1f678",
  "timestamp": "2025-09-08T03:07:24.637Z",
  "session_id": "session_1757300624739_cz2adzlkj",
  "events": [
    {
      "id": "612b2d01a507c7f3",
      "type": "state_change",
      "timestamp": "2025-09-08T03:07:24.547Z",
      "session_id": "session_1757300624739_cz2adzlkj",
      "file_path": "/Users/kavi/Sharedcodingprojects/Muralla-4.0/.shared-state/.shared-state/sessions/session_1757300624739_cz2adzlkj.json",
      "change_type": "modification"
    }
  ]
}