{
  "batch_id": "67da0773362a98d4",
  "timestamp": "2025-09-08T03:14:30.199Z",
  "session_id": "session_1757300624739_cz2adzlkj",
  "events": [
    {
      "id": "31869a8960c21616",
      "type": "state_change",
      "timestamp": "2025-09-08T03:14:30.168Z",
      "session_id": "session_1757300624739_cz2adzlkj",
      "file_path": "/Users/kavi/Sharedcodingprojects/Muralla-4.0/.shared-state/.shared-state/sessions/session_1757300624739_cz2adzlkj.json",
      "change_type": "modification"
    }
  ]
}