{
  "batch_id": "4de53a8a35cd3f3e",
  "timestamp": "2025-09-08T03:11:12.105Z",
  "session_id": "session_1757300624739_cz2adzlkj",
  "events": [
    {
      "id": "ae556b1cf7ef1066",
      "type": "state_change",
      "timestamp": "2025-09-08T03:11:12.059Z",
      "session_id": "session_1757300624739_cz2adzlkj",
      "file_path": "/Users/kavi/Sharedcodingprojects/Muralla-4.0/.shared-state/.shared-state/sessions/session_1757300624739_cz2adzlkj.json",
      "change_type": "modification"
    }
  ]
}