{
  "batch_id": "81494c975fe4536b",
  "timestamp": "2025-09-08T03:08:42.873Z",
  "session_id": "session_1757300624739_cz2adzlkj",
  "events": [
    {
      "id": "722b030cbdb4cc34",
      "type": "state_change",
      "timestamp": "2025-09-08T03:08:42.853Z",
      "session_id": "session_1757300624739_cz2adzlkj",
      "file_path": "/Users/kavi/Sharedcodingprojects/Muralla-4.0/.shared-state/.shared-state/sessions/session_1757300624739_cz2adzlkj.json",
      "change_type": "modification"
    }
  ]
}