{
  "batch_id": "161ca6a4dbaec2ca",
  "timestamp": "2025-09-08T03:04:01.730Z",
  "session_id": "session_1757300624739_cz2adzlkj",
  "events": [
    {
      "id": "fe03624bd127ac8f",
      "type": "state_change",
      "timestamp": "2025-09-08T03:04:01.703Z",
      "session_id": "session_1757300624739_cz2adzlkj",
      "file_path": "/Users/kavi/Sharedcodingprojects/Muralla-4.0/.shared-state/.shared-state/sessions/session_1757300624739_cz2adzlkj.json",
      "change_type": "modification"
    }
  ]
}