{
  "batch_id": "4015ab3f37842048",
  "timestamp": "2025-09-08T03:06:31.478Z",
  "session_id": "session_1757300624739_cz2adzlkj",
  "events": [
    {
      "id": "c5850e85f0e45f1e",
      "type": "state_change",
      "timestamp": "2025-09-08T03:06:31.388Z",
      "session_id": "session_1757300624739_cz2adzlkj",
      "file_path": "/Users/kavi/Sharedcodingprojects/Muralla-4.0/.shared-state/.shared-state/sessions/session_1757300624739_cz2adzlkj.json",
      "change_type": "modification"
    }
  ]
}