{
  "batch_id": "3a565b2a63af8534",
  "timestamp": "2025-09-08T03:09:25.277Z",
  "session_id": "session_1757300624739_cz2adzlkj",
  "events": [
    {
      "id": "c40cf59279a94a7b",
      "type": "state_change",
      "timestamp": "2025-09-08T03:09:25.270Z",
      "session_id": "session_1757300624739_cz2adzlkj",
      "file_path": "/Users/kavi/Sharedcodingprojects/Muralla-4.0/.shared-state/.shared-state/sessions/session_1757300624739_cz2adzlkj.json",
      "change_type": "modification"
    }
  ]
}