{
  "batch_id": "915c1ca69136c5b0",
  "timestamp": "2025-09-08T03:04:09.438Z",
  "session_id": "session_1757300624739_cz2adzlkj",
  "events": [
    {
      "id": "d83a4707796e5abd",
      "type": "state_change",
      "timestamp": "2025-09-08T03:04:09.361Z",
      "session_id": "session_1757300624739_cz2adzlkj",
      "file_path": "/Users/kavi/Sharedcodingprojects/Muralla-4.0/.shared-state/.shared-state/sessions/session_1757300624739_cz2adzlkj.json",
      "change_type": "modification"
    }
  ]
}