{
  "batch_id": "d5aa10c1b460328c",
  "timestamp": "2025-09-08T03:08:29.397Z",
  "session_id": "session_1757300624739_cz2adzlkj",
  "events": [
    {
      "id": "f94c620bff6ab004",
      "type": "state_change",
      "timestamp": "2025-09-08T03:08:29.334Z",
      "session_id": "session_1757300624739_cz2adzlkj",
      "file_path": "/Users/kavi/Sharedcodingprojects/Muralla-4.0/.shared-state/.shared-state/sessions/session_1757300624739_cz2adzlkj.json",
      "change_type": "modification"
    }
  ]
}