{
  "batch_id": "7014ce1426cfa7b9",
  "timestamp": "2025-09-08T03:13:47.222Z",
  "session_id": "session_1757300624739_cz2adzlkj",
  "events": [
    {
      "id": "53aeda87dce12825",
      "type": "state_change",
      "timestamp": "2025-09-08T03:13:47.178Z",
      "session_id": "session_1757300624739_cz2adzlkj",
      "file_path": "/Users/kavi/Sharedcodingprojects/Muralla-4.0/.shared-state/.shared-state/sessions/session_1757300624739_cz2adzlkj.json",
      "change_type": "modification"
    }
  ]
}