{
  "batch_id": "2f81117f2ad5f613",
  "timestamp": "2025-09-08T03:12:06.343Z",
  "session_id": "session_1757300624739_cz2adzlkj",
  "events": [
    {
      "id": "df8ecc8faeac1e58",
      "type": "state_change",
      "timestamp": "2025-09-08T03:12:06.300Z",
      "session_id": "session_1757300624739_cz2adzlkj",
      "file_path": "/Users/kavi/Sharedcodingprojects/Muralla-4.0/.shared-state/.shared-state/sessions/session_1757300624739_cz2adzlkj.json",
      "change_type": "modification"
    }
  ]
}