{
  "batch_id": "c751f21796dd9ba6",
  "timestamp": "2025-09-08T03:13:04.003Z",
  "session_id": "session_1757300624739_cz2adzlkj",
  "events": [
    {
      "id": "3ec3077d63153d81",
      "type": "state_change",
      "timestamp": "2025-09-08T03:13:03.912Z",
      "session_id": "session_1757300624739_cz2adzlkj",
      "file_path": "/Users/kavi/Sharedcodingprojects/Muralla-4.0/.shared-state/.shared-state/sessions/session_1757300624739_cz2adzlkj.json",
      "change_type": "modification"
    }
  ]
}