{
  "batch_id": "964b955bbfa90e29",
  "timestamp": "2025-09-08T03:05:55.815Z",
  "session_id": "session_1757300624739_cz2adzlkj",
  "events": [
    {
      "id": "8c07187f67249970",
      "type": "state_change",
      "timestamp": "2025-09-08T03:05:55.733Z",
      "session_id": "session_1757300624739_cz2adzlkj",
      "file_path": "/Users/kavi/Sharedcodingprojects/Muralla-4.0/.shared-state/.shared-state/sessions/session_1757300624739_cz2adzlkj.json",
      "change_type": "modification"
    }
  ]
}